litequeue.py
litequeue-0.9.dist-info/LICENSE
litequeue-0.9.dist-info/METADATA
litequeue-0.9.dist-info/WHEEL
litequeue-0.9.dist-info/top_level.txt
litequeue-0.9.dist-info/RECORD
