Metadata-Version: 2.1
Name: litequeue
Version: 0.9
Summary: Simple queue built on top of SQLite
Home-page: https://github.com/litements/litequeue
Author: Ricardo Ander-Egg Aguilar
Author-email: rsubacc@gmail.com
Classifier: Operating System :: OS Independent
Requires-Python: >=3.6
License-File: LICENSE
